micromelon/__init__.py
micromelon/_binary.py
micromelon/_mm_logging.py
micromelon/_singleton.py
micromelon/_utils.py
micromelon/_robot_comms/__init__.py
micromelon/_robot_comms/_comms_constants.py
micromelon/_robot_comms/_moving_average.py
micromelon/_robot_comms/_robot_communicator_threaded.py
micromelon/_robot_comms/_rover_controller.py
micromelon/_robot_comms/_rover_read_cache.py
micromelon/_robot_comms/_thread_command.py
micromelon/_robot_comms/ble/__init__.py
micromelon/_robot_comms/ble/_ble_controller.py
micromelon/_robot_comms/ble/_ble_controller_threadwrapped.py
micromelon/_robot_comms/transports/__init__.py
micromelon/_robot_comms/transports/_robot_transport_base.py
micromelon/_robot_comms/transports/_robot_transport_ble.py
micromelon/_robot_comms/transports/_robot_transport_serial.py
micromelon/_robot_comms/transports/_robot_transport_tcp.py
micromelon/_robot_comms/transports/_serial_tcp_connection.py
micromelon/_robot_comms/uart/__init__.py
micromelon/_robot_comms/uart/_uart.py
micromelon/battery/__init__.py
micromelon/battery/_battery.py
micromelon/colour/__init__.py
micromelon/colour/_colour.py
micromelon/helper_math/__init__.py
micromelon/helper_math/_math.py
micromelon/i2c/__init__.py
micromelon/i2c/_i2c.py
micromelon/imu/__init__.py
micromelon/imu/_imu.py
micromelon/ir/__init__.py
micromelon/ir/_ir.py
micromelon/leds/__init__.py
micromelon/leds/_leds.py
micromelon/motors/__init__.py
micromelon/motors/_motors.py
micromelon/robot/__init__.py
micromelon/robot/_robot.py
micromelon/servos/__init__.py
micromelon/servos/_servos.py
micromelon/sounds/__init__.py
micromelon/sounds/_notes.py
micromelon/sounds/_sounds.py
micromelon/ultrasonic/__init__.py
micromelon/ultrasonic/_ultrasonic.py
micromelon-1.2.0.dist-info/licenses/LICENSE
micromelon-1.2.0.dist-info/METADATA
micromelon-1.2.0.dist-info/WHEEL
micromelon-1.2.0.dist-info/top_level.txt
micromelon-1.2.0.dist-info/RECORD
