Metadata-Version: 2.4
Name: micromelon
Version: 1.2.0
Summary: A Python module to control Micromelon Robots over BLE, TCP, or Serial with a Raspberry Pi connected to the rover
Home-page: https://github.com/Micromelon-Robotics/mm-pymodule
Author: Micromelon Robotics
Author-email: contact@micromelon.com.au
Project-URL: Bug Tracker, https://github.com/Micromelon-Robotics/mm-pymodule/issues
Classifier: Development Status :: 4 - Beta
Classifier: Framework :: AsyncIO
Classifier: Intended Audience :: Education
Classifier: Intended Audience :: Developers
Classifier: Topic :: Education
Classifier: Topic :: Communications
Classifier: License :: OSI Approved :: MIT License
Classifier: Natural Language :: English
Classifier: Operating System :: Microsoft :: Windows :: Windows 10
Classifier: Operating System :: POSIX :: Linux
Classifier: Operating System :: MacOS :: MacOS X
Classifier: Programming Language :: Python
Classifier: Programming Language :: Python :: 3
Classifier: Programming Language :: Python :: 3.8
Classifier: Programming Language :: Python :: 3.9
Classifier: Programming Language :: Python :: 3.10
Classifier: Programming Language :: Python :: 3.11
Classifier: Programming Language :: Python :: 3.12
Requires-Python: >=3.8
License-File: LICENSE
Requires-Dist: bleak<1.2.0,>=1.1.0
Requires-Dist: pyserial<3.6,>=3.5
Requires-Dist: numpy<2.0.0,>=1.20.0
Dynamic: license-file
